phpbridge/__init__.py
phpbridge/classes.py
phpbridge/docblocks.py
phpbridge/functions.py
phpbridge/modules.py
phpbridge/objects.py
phpbridge/server.php
phpbridge/utils.py
phpbridge/php-server/CommandServer.php
phpbridge/php-server/Commands.php
phpbridge/php-server/NonFunctionProxy.php
phpbridge/php-server/ObjectStore.php
phpbridge/php-server/StdioCommandServer.php
phpbridge/php-server/Exceptions/AttributeError.php
phpbridge/php-server/Exceptions/ConnectionLostException.php
phpbridge/php-server/Representer/PythonRepresenter.php
phpbridge/php-server/Representer/Representer.php
phpbridge/php-server/Representer/RepresenterInterface.php
phpbridge-0.0.3.dist-info/DESCRIPTION.rst
phpbridge-0.0.3.dist-info/METADATA
phpbridge-0.0.3.dist-info/RECORD
phpbridge-0.0.3.dist-info/WHEEL
phpbridge-0.0.3.dist-info/metadata.json
phpbridge-0.0.3.dist-info/top_level.txt
