Metadata-Version: 2.0
Name: phpbridge
Version: 0.0.3
Summary: Import PHP code into Python
Home-page: https://github.com/blyxxyz/Python-PHP-Bridge
Author: Jan Verbeek
Author-email: jan.verbeek@posteo.nl
License: ISC
Platform: UNKNOWN
Classifier: Programming Language :: PHP
Classifier: Programming Language :: Python :: 3
Classifier: Programming Language :: Python :: 3
Classifier: Programming Language :: Python :: 3 :: Only
Classifier: Programming Language :: Python :: 3.5
Classifier: License :: OSI Approved :: ISC License (ISCL)
